LICENSE
MANIFEST.in
README.rst
setup.cfg
setup.py
django_etcd_settings.egg-info/PKG-INFO
django_etcd_settings.egg-info/SOURCES.txt
django_etcd_settings.egg-info/dependency_links.txt
django_etcd_settings.egg-info/not-zip-safe
django_etcd_settings.egg-info/requires.txt
django_etcd_settings.egg-info/top_level.txt
docs/Makefile
docs/conf.py
docs/index.rst
docs/installation.rst
docs/make.bat
docs/usage.rst
etcd_settings/__init__.py
etcd_settings/apps.py
etcd_settings/loader.py
etcd_settings/manager.py
etcd_settings/proxy.py
etcd_settings/utils.py
tests/__init__.py
tests/conftest.py
tests/loader_dev_params.py
tests/test_loader.py
tests/test_manager.py
tests/test_proxy.py
tests/test_utils.py
tests/unicode.txt