Metadata-Version: 1.1
Name: django-etcd-settings
Version: 0.1.15
Summary: A dynamic settings management solution for Django using ETCD
Home-page: https://github.com/kpn-digital/django-etcd-settings
Author: Enrique Paz
Author-email: quiquepaz@gmail.com
License: UNKNOWN
Platform: UNKNOWN
Classifier: Development Status :: 5 - Production/Stable
Classifier: Environment :: Web Environment
Classifier: Intended Audience :: Developers
Classifier: Operating System :: OS Independent
Classifier: Programming Language :: Python
Classifier: Programming Language :: Python :: 2
Classifier: Programming Language :: Python :: 2.7
Classifier: Topic :: Internet :: WWW/HTTP
